{"success":true,"registrations":[{"orderId":"SSS2025-1757136910989-fqwtbv","fullName":"Test User","phone":"+62812345678","email":"test@example.com","dob":"1990-01-01","address":"Test Address 123","country":"Indonesia","amount":250000,"status":"paid","id":"REG_1757136911602_huxv0cm6b","createdAt":"2025-09-06T05:35:11.602Z","updatedAt":"2025-09-06T05:35:27.741Z"},{"orderId":"SSS2025-1757137811064-sae6bb","fullName":"Syifa Ali Zulkarnaen","phone":"085881350398","email":"azulkarnaen7@gmail.com","dob":"2000-05-01","address":"Jl. Raya Perum Korpri Blok i8 no.6","country":"Indonesia","amount":250000,"status":"paid","id":"REG_1757137811572_a7jhf8lyw","createdAt":"2025-09-06T05:50:11.572Z","updatedAt":"2025-09-06T06:03:25.262Z"},{"orderId":"SSS2025-1757138706650-cm17dp","fullName":"Amir Komarudin","phone":"08588822664455","email":"zulkarnaens0205@gmail.com","dob":"1998-03-24","address":"Jl. Bintaro jaya jaya jaya","country":"Indonesia","amount":250000,"status":"pending","id":"REG_1757138707197_vtn903kjj","createdAt":"2025-09-06T06:05:07.197Z","updatedAt":"2025-09-06T06:05:07.197Z"},{"orderId":"SSS2025-1757237727250-t3xdga","fullName":"Ali Zulkarnaen","phone":"085881350398","email":"akunffa@gmail.com","dob":"2000-09-12","address":"Rawa Simprug","country":"Indonesia","amount":250000,"status":"pending","id":"REG_1757237727860_hyccfdc1r","createdAt":"2025-09-07T09:35:27.860Z","updatedAt":"2025-09-07T09:35:27.860Z"}],"count":4}